{
  "version": 2,
  "settings": {
      "layout": {
          "contentSize": "840px",
          "wideSize": "1100px"
      },
      "border": {
        "radius": true,
        "color": true
      },
      "spacing": {
        "blockGap": true,
        "margin": true,
        "padding": true
      },        
      "color": {
          "palette": [
              {
                "slug": "primary",
                "color": "#0073aa",
                "name": "Primary"
              },
              {
                "slug": "secondary",
                "color": "#005177",
                "name": "Secondary"
              },
              {
                "slug": "accent",
                "color": "#000000",
                "name": "Accent"
              }
          ]
      },
      "typography": {
        "fontFamilies": [
          {
            "fontFace": [
              {
                "fontFamily": "Protest Strike",
                "fontWeight": "400",
                "fontStretch": "normal",
                "fontStyle": "normal",
                "src": ["file:./fonts/proteststrike.woff2"]
              }
            ],
            "fontFamily": "\"Protest Strike\", sans-serif",
            "name": "Heading Font",
            "slug": "headings"
          },
          {
            "fontFace": [
              {
                "fontFamily": "Poppins",
                "fontWeight": "400",
                "fontStretch": "normal",
                "fontStyle": "normal",
                "src": ["file:./fonts/poppins.woff2"]
              }
            ],
            "fontFamily": "\"Poppins\", sans-serif",
            "name": "Body Font",
            "slug": "body"
          }
        ],
        "fontSizes": [
          {
              "slug": "small",
              "size": "16px",
              "name": "16px"
          },
          {
              "slug": "medium",
              "size": "20px",
              "name": "20px"
          },
          {
              "slug": "large",
              "size": "24px",
              "name": "24px"
          },
          {
              "slug": "xlarge",
              "size": "36px",
              "name": "36px"
          },
          {
              "slug": "xxlarge",
              "size": "48px",
              "name": "48px"
          },
          {
              "slug": "xxxlarge",
              "size": "64px",
              "name": "64px"
          }
        ],
        "lineHeight": true
      }
  },

  "styles": {
    "spacing": {
      "blockGap": "0"
    },
    "blocks": {
      "core/site-tagline": {
        "typography": {
          "fontWeight": "bold",
          "textTransform": "uppercase"
        }
      },
      "core/navigation": {
        "typography": {
          "fontFamily": "Protest Strike"
        },
        "spacing": {
          "blockGap": true,
          "margin": true,
          "padding": true
        }
      },
      "core/heading": {
        "typography": {
          "fontFamily": "Protest Strike"
        }
      },
      "core/paragraph": {
        "typography": {
          "fontFamily": "Poppins"
        }
      },
      "core/button": {
        "typography": {
          "fontFamily": "Protest Strike"
        }
      },
      "core/link": {
        "typography": {
          "fontFamily": "Protest Strike"
        }
      }
    },
    "elements": {
      "link": {
        "typography": {
          "textDecoration": "none"
        }
      },
      "h1": {
        "typography": {
          "fontSize": "64px"
        }
      },
      "h2": {
        "typography": {
          "fontSize": "48px"
        }
      },
      "h3": {
        "typography": {
          "fontSize": "36px"
        }
      },
      "h4": {
        "typography": {
          "fontSize": "24px"
        }
      }
    }
  },
  "templateParts": [
    {
      "name": "header",
      "area": "header",
      "title": "Header"
    },
    {
      "name": "footer",
      "area": "footer",
      "title": "Footer"
    }
  ]
} 